tg_react/__init__.py
tg_react/api/__init__.py
tg_react/api/accounts/__init__.py
tg_react/api/accounts/serializers.py
tg_react/api/accounts/urls.py
tg_react/api/accounts/views.py
tg_react/apps.py
tg_react/locale/en/LC_MESSAGES/django.mo
tg_react/locale/en/LC_MESSAGES/django.po
tg_react/locale/en_US/LC_MESSAGES/django.mo
tg_react/locale/en_US/LC_MESSAGES/django.po
tg_react/locale/et/LC_MESSAGES/django.mo
tg_react/locale/et/LC_MESSAGES/django.po
tg_react/locale/ru/LC_MESSAGES/django.mo
tg_react/locale/ru/LC_MESSAGES/django.po
tg_react/middleware.py
tg_react/routers.py
tg_react/settings.py
tg_react/templates/tg_react_emails/base.txt
tg_react/templates/tg_react_emails/password_reset.html
tg_react/templates/tg_react_emails/password_reset.txt
tg_react-3.1.0.dist-info/LICENSE
tg_react-3.1.0.dist-info/WHEEL
tg_react-3.1.0.dist-info/METADATA
tg_react-3.1.0.dist-info/RECORD
