Metadata-Version: 2.1
Name: tg-react
Version: 3.1.0
Summary: Helpers for react based applications running on django.
Home-page: https://github.com/thorgate/tg-react
License: BSD
Keywords: tg-react,thorgate,rest,drf
Author: Thorgate
Author-email: code@thorgate.eu
Requires-Python: >=3.7,<4
Classifier: Development Status :: 5 - Production/Stable
Classifier: Framework :: Django
Classifier: Intended Audience :: Developers
Classifier: License :: OSI Approved :: BSD License
Classifier: License :: Other/Proprietary License
Classifier: Natural Language :: English
Classifier: Programming Language :: Python :: 3
Classifier: Programming Language :: Python :: 3.7
Classifier: Programming Language :: Python :: 3.8
Classifier: Programming Language :: Python :: 3.9
Classifier: Programming Language :: Python :: 3.10
Classifier: Programming Language :: Python :: 3.11
Classifier: Programming Language :: Python :: 3
Classifier: Programming Language :: Python :: 3.10
Classifier: Programming Language :: Python :: 3.7
Classifier: Programming Language :: Python :: 3.8
Classifier: Programming Language :: Python :: 3.9
Requires-Dist: django (>=2.2,<4.2)
Requires-Dist: djangorestframework (>=3.9.2)
Project-URL: Repository, https://github.com/thorgate/tg-react
